Metadata-Version: 2.1
Name: iseq-prof
Version: 0.0.4
Summary: ISEQ profiling
Home-page: https://github.com/EBI-Metagenomics/iseq-prof
Author: Danilo Horta
Author-email: horta@ebi.ac.uk
Maintainer: Danilo Horta
Maintainer-email: horta@ebi.ac.uk
License: MIT
Download-URL: https://github.com/EBI-Metagenomics/iseq-prof
Keywords: iseq,prof
Platform: Windows
Platform: MacOS
Platform: Linux
Classifier: Development Status :: 5 - Production/Stable
Classifier: License :: OSI Approved :: MIT License
Classifier: Operating System :: OS Independent
Classifier: Programming Language :: Python
Requires-Dist: Deprecated (>=1.2.10)
Requires-Dist: appdirs (>=1.4.4)
Requires-Dist: assertpy (>=1.1)
Requires-Dist: biopython (>=1.78)
Requires-Dist: click (>=7.1.2)
Requires-Dist: diskcache (>=5.0.3)
Requires-Dist: fasta-reader (>=1.0.0)
Requires-Dist: gff-io (>=0.0.2)
Requires-Dist: hmmer-reader (>=0.0.14)
Requires-Dist: hmmer (>=0.0.12)
Requires-Dist: iseq (>=0.0.13)
Requires-Dist: lttb (>=0.2.2)
Requires-Dist: numba (>=0.50.1)
Requires-Dist: numpy (>=1.18.1)
Requires-Dist: pandas (>=1.1.2)
Requires-Dist: plotly (>=4.8.2)
Requires-Dist: pooch (>=1.2.0)
Requires-Dist: pysam
Requires-Dist: pytest (>=5.3.5)
Requires-Dist: tabulate (>=0.8.7)
